corgidrp/__init__.py
corgidrp/astrom.py
corgidrp/bad_pixel_calibration.py
corgidrp/caldb.py
corgidrp/calibrate_kgain.py
corgidrp/calibrate_nonlin.py
corgidrp/check.py
corgidrp/combine.py
corgidrp/corethroughput.py
corgidrp/darks.py
corgidrp/data.py
corgidrp/detector.py
corgidrp/find_source.py
corgidrp/flat.py
corgidrp/fluxcal.py
corgidrp/klip_fm.py
corgidrp/l1_to_l2a.py
corgidrp/l2a_to_l2b.py
corgidrp/l2b_to_l3.py
corgidrp/l3_to_l4.py
corgidrp/l4_to_tda.py
corgidrp/measure_companions.py
corgidrp/mocks.py
corgidrp/nd_filter_calibration.py
corgidrp/ops.py
corgidrp/photon_counting.py
corgidrp/pump_trap_calibration.py
corgidrp/sorting.py
corgidrp/star_center.py
corgidrp/walker.py
corgidrp-2.2.dist-info/LICENSE
corgidrp-2.2.dist-info/METADATA
corgidrp-2.2.dist-info/WHEEL
corgidrp-2.2.dist-info/top_level.txt
corgidrp-2.2.dist-info/RECORD
