Metadata-Version: 2.1
Name: corgidrp
Version: 2.2
Summary: (Roman Space Telescope) CORonaGraph Instrument Data Reduction Pipeline
Home-page: https://github.com/roman-corgi/corgidrp
Author: Roman Coronagraph Instrument CPP
License: BSD
Keywords: Roman Space Telescope Exoplanets Astronomy
Classifier: Intended Audience :: Science/Research
Classifier: Topic :: Scientific/Engineering :: Astronomy
Classifier: Programming Language :: Python :: 3
License-File: LICENSE
Requires-Dist: astropy
Requires-Dist: matplotlib
Requires-Dist: numpy
Requires-Dist: pandas
Requires-Dist: pytest
Requires-Dist: scipy
Requires-Dist: photutils >=2.0.0
Requires-Dist: statsmodels
Requires-Dist: pyklip
Requires-Dist: emccd-detect
Requires-Dist: tqdm
Requires-Dist: termcolor
